pyopcode.cp38-win_amd64.pyd
pyopcode-0.4.0.dist-info/METADATA
pyopcode-0.4.0.dist-info/WHEEL
pyopcode-0.4.0.dist-info/top_level.txt
pyopcode-0.4.0.dist-info/RECORD
