Metadata-Version: 2.1
Name: pyopcode
Version: 0.4.0
Summary: OPCODE python bindings
Home-page: https://github.com/ClinicalGraphics/pyopcode/
Author: Korijn van Golen
Author-email: korijn.vangolen@zimmerbiomet.com
License: UNKNOWN
Platform: UNKNOWN
Requires-Python: >=3.6.0
Requires-Dist: numpy (>=1.15.0)
Provides-Extra: dev
Requires-Dist: pytest ; extra == 'dev'
Requires-Dist: black ; extra == 'dev'
